e_x-1.16.0.data/scripts/electrumx_compact_history
e_x-1.16.0.data/scripts/electrumx_rpc
e_x-1.16.0.data/scripts/electrumx_server
electrumx/__init__.py
electrumx/lib/__init__.py
electrumx/lib/coins.py
electrumx/lib/enum.py
electrumx/lib/env_base.py
electrumx/lib/hash.py
electrumx/lib/merkle.py
electrumx/lib/peer.py
electrumx/lib/script.py
electrumx/lib/server_base.py
electrumx/lib/text.py
electrumx/lib/tx.py
electrumx/lib/tx_axe.py
electrumx/lib/tx_dash.py
electrumx/lib/util.py
electrumx/server/__init__.py
electrumx/server/block_processor.py
electrumx/server/controller.py
electrumx/server/daemon.py
electrumx/server/db.py
electrumx/server/env.py
electrumx/server/history.py
electrumx/server/mempool.py
electrumx/server/peers.py
electrumx/server/session.py
electrumx/server/storage.py
e_x-1.16.0.dist-info/LICENCE
e_x-1.16.0.dist-info/METADATA
e_x-1.16.0.dist-info/WHEEL
e_x-1.16.0.dist-info/top_level.txt
e_x-1.16.0.dist-info/RECORD
